sati/__init__.py
sati/distributions.py
sati/model.py
sati/objective.py
sati/optimize.py
sati/planes.py
sati/preprocessing.py
sati-1.0.0.dist-info/LICENSE
sati-1.0.0.dist-info/WHEEL
sati-1.0.0.dist-info/METADATA
sati-1.0.0.dist-info/RECORD
