Metadata-Version: 2.1
Name: sati
Version: 1.0.0
Summary: Statistical analysis of topographic image
Home-page: https://github.com/yuksk/sati/
License: MIT
Author: Yuhki Kohsaka
Author-email: yuhki.kohsaka@gmail.com
Requires-Python: >=3.8,<4.0
Classifier: License :: OSI Approved :: MIT License
Classifier: Programming Language :: Python :: 3
Classifier: Programming Language :: Python :: 3.8
Classifier: Programming Language :: Python :: 3.9
Requires-Dist: matplotlib (>=3.3.1,<4.0.0)
Requires-Dist: numexpr (>=2.7.1,<3.0.0)
Requires-Dist: numpy (>=1.18.0,<2.0.0)
Requires-Dist: scipy (>=1.5.0,<2.0.0)
Project-URL: Documentation, https://yuksk.github.io/sati/index.html
Project-URL: Repository, https://github.com/yuksk/sati/
